numprims/__init__.py
numprims-1.0.dist-info/LICENSE
numprims-1.0.dist-info/METADATA
numprims-1.0.dist-info/WHEEL
numprims-1.0.dist-info/top_level.txt
numprims-1.0.dist-info/RECORD
